doorman/__init__.py
doorman/__main__.py
doorman/assets/__init__.py
doorman/assets/sprite_generator.py
doorman/assets/sprites.py
doorman/auth/clerk_client.py
doorman/billing/__init__.py
doorman/billing/clerk_integration.py
doorman/billing/manager.py
doorman/billing/models.py
doorman/billing/providers.py
doorman/cli/__init__.py
doorman/cli/auth.py
doorman/cli/config.py
doorman/cli/main.py
doorman/cli/providers.py
doorman/config/__init__.py
doorman/config/manager.py
doorman/core/__init__.py
doorman/core/database.py
doorman/core/intent_engine.py
doorman/core/models.py
doorman/core/pattern_library.py
doorman/core/planner.py
doorman/core/script_engine.py
doorman/core/taxonomy.py
doorman/core/tier_guard.py
doorman/mcp_client/__init__.py
doorman/mcp_client/client.py
doorman/mcp_server/__init__.py
doorman/mcp_server/server.py
doorman/plugins/__init__.py
doorman/plugins/manager.py
doorman/plugins/sdk.py
doorman/plugins/bundled/analyst/README.md
doorman/plugins/bundled/analyst/__init__.py
doorman/plugins/bundled/analyst/analyst_plugin.py
doorman/plugins/bundled/analyst/config.example.json
doorman/plugins/bundled/analyst/plugin.toml
doorman/plugins/bundled/developer/README.md
doorman/plugins/bundled/developer/__init__.py
doorman/plugins/bundled/developer/config.example.json
doorman/plugins/bundled/developer/developer_plugin.py
doorman/plugins/bundled/developer/plugin.toml
doorman/plugins/bundled/gdrive/README.md
doorman/plugins/bundled/gdrive/__init__.py
doorman/plugins/bundled/gdrive/config.example.json
doorman/plugins/bundled/gdrive/gdrive_plugin.py
doorman/plugins/bundled/gdrive/plugin.toml
doorman/plugins/bundled/github/README.md
doorman/plugins/bundled/github/__init__.py
doorman/plugins/bundled/github/config.example.json
doorman/plugins/bundled/github/github_plugin.py
doorman/plugins/bundled/github/plugin.toml
doorman/plugins/bundled/jira/README.md
doorman/plugins/bundled/jira/__init__.py
doorman/plugins/bundled/jira/config.example.json
lobby_ai-1.1.1.dist-info/METADATA
lobby_ai-1.1.1.dist-info/WHEEL
lobby_ai-1.1.1.dist-info/entry_points.txt
lobby_ai-1.1.1.dist-info/licenses/LICENSE
lobby_ai-1.1.1.dist-info/RECORD
