Metadata-Version: 2.4
Name: lobby-ai
Version: 1.1.1
Summary: 🏢 LOBBY - AI concierge service that multiplies your existing CLI tools
Project-URL: Homepage, https://lobby.directory
Project-URL: Repository, https://github.com/franco/lobby-ai
Project-URL: Documentation, https://lobby.directory/docs
Project-URL: Bug Reports, https://github.com/franco/lobby-ai/issues
Author-email: Franco <support@lobby.directory>
License: MIT
License-File: LICENSE
Keywords: ai,claude,cli,concierge,cursor,gemini,mcp,orchestration
Classifier: Development Status :: 5 - Production/Stable
Classifier: Environment :: Console
Classifier: Intended Audience :: Developers
Classifier: License :: OSI Approved :: MIT License
Classifier: Programming Language :: Python :: 3
Classifier: Programming Language :: Python :: 3.8
Classifier: Programming Language :: Python :: 3.9
Classifier: Programming Language :: Python :: 3.10
Classifier: Programming Language :: Python :: 3.11
Classifier: Programming Language :: Python :: 3.12
Classifier: Topic :: Scientific/Engineering :: Artificial Intelligence
Classifier: Topic :: Software Development :: Libraries :: Python Modules
Requires-Python: >=3.8
Requires-Dist: cryptography>=41.0.0
Requires-Dist: httpx>=0.24.0
Requires-Dist: pydantic>=2.0.0
Requires-Dist: rich>=13.0.0
Requires-Dist: typer>=0.9.0
Provides-Extra: all
Requires-Dist: flask-cors>=4.0.0; extra == 'all'
Requires-Dist: flask>=2.3.0; extra == 'all'
Requires-Dist: inquirerpy>=0.3.4; extra == 'all'
Requires-Dist: mcp>=1.0.0; extra == 'all'
Requires-Dist: prompt-toolkit<4.0.0,>=3.0.0; extra == 'all'
Requires-Dist: questionary>=2.0.0; extra == 'all'
Requires-Dist: stripe>=5.0.0; extra == 'all'
Provides-Extra: billing
Requires-Dist: flask-cors>=4.0.0; extra == 'billing'
Requires-Dist: flask>=2.3.0; extra == 'billing'
Requires-Dist: stripe>=5.0.0; extra == 'billing'
Provides-Extra: dev
Requires-Dist: mypy>=1.7.0; extra == 'dev'
Requires-Dist: pre-commit>=3.6.0; extra == 'dev'
Requires-Dist: pytest-asyncio>=0.21.0; extra == 'dev'
Requires-Dist: pytest-cov>=4.1.0; extra == 'dev'
Requires-Dist: pytest>=7.4.0; extra == 'dev'
Requires-Dist: ruff>=0.5.0; extra == 'dev'
Provides-Extra: interactive
Requires-Dist: inquirerpy>=0.3.4; extra == 'interactive'
Requires-Dist: prompt-toolkit<4.0.0,>=3.0.0; extra == 'interactive'
Requires-Dist: questionary>=2.0.0; extra == 'interactive'
Provides-Extra: mcp
Requires-Dist: mcp>=1.0.0; extra == 'mcp'
